odoo/addons/sale_pricelist_triple_discount/README.rst
odoo/addons/sale_pricelist_triple_discount/__init__.py
odoo/addons/sale_pricelist_triple_discount/__manifest__.py
odoo/addons/sale_pricelist_triple_discount/i18n/it.po
odoo/addons/sale_pricelist_triple_discount/i18n/sale_pricelist_triple_discount.pot
odoo/addons/sale_pricelist_triple_discount/model/__init__.py
odoo/addons/sale_pricelist_triple_discount/model/pricelist.py
odoo/addons/sale_pricelist_triple_discount/model/sale.py
odoo/addons/sale_pricelist_triple_discount/readme/CONFIGURE.rst
odoo/addons/sale_pricelist_triple_discount/readme/CONTRIBUTORS.rst
odoo/addons/sale_pricelist_triple_discount/readme/DESCRIPTION.rst
odoo/addons/sale_pricelist_triple_discount/readme/USAGE.rst
odoo/addons/sale_pricelist_triple_discount/static/description/icon.png
odoo/addons/sale_pricelist_triple_discount/static/description/index.html
odoo/addons/sale_pricelist_triple_discount/tests/__init__.py
odoo/addons/sale_pricelist_triple_discount/tests/test_sale_order.py
odoo/addons/sale_pricelist_triple_discount/view/product_pricelist_item_views.xml
odoo_addon_sale_pricelist_triple_discount-16.0.1.0.0.3.dist-info/METADATA
odoo_addon_sale_pricelist_triple_discount-16.0.1.0.0.3.dist-info/WHEEL
odoo_addon_sale_pricelist_triple_discount-16.0.1.0.0.3.dist-info/top_level.txt
odoo_addon_sale_pricelist_triple_discount-16.0.1.0.0.3.dist-info/RECORD
